reprokit/__init__.py
reprokit/cli.py
reprokit/config.py
reprokit/config_templates.py
reprokit/datahash.py
reprokit/determinism.py
reprokit/env_freeze.py
reprokit/logging.py
reprokit/manifest.py
reprokit/utils.py
reprokit/hooks/check_manifest.py
reprokit/hooks/guard_seed.py
reprokit_ml-0.1.0.dist-info/METADATA
reprokit_ml-0.1.0.dist-info/WHEEL
reprokit_ml-0.1.0.dist-info/entry_points.txt
reprokit_ml-0.1.0.dist-info/licenses/LICENSE
reprokit_ml-0.1.0.dist-info/RECORD
