Metadata-Version: 2.4
Name: reprokit-ml
Version: 0.1.0
Summary: One-command determinism + manifest for ML projects.
Project-URL: Homepage, https://github.com/abdulvahapmutlu/reprokit-ml
Project-URL: Issues, https://github.com/abdulvahapmutlu/reprokit-ml/issues
Author: Abdulvahap Mutlu
License: MIT
License-File: LICENSE
Keywords: determinism,hashing,manifest,mlops,reproducibility
Classifier: License :: OSI Approved :: MIT License
Classifier: Operating System :: OS Independent
Classifier: Programming Language :: Python :: 3
Classifier: Programming Language :: Python :: 3 :: Only
Classifier: Programming Language :: Python :: 3.10
Classifier: Programming Language :: Python :: 3.11
Classifier: Programming Language :: Python :: 3.12
Requires-Python: >=3.10
Requires-Dist: pathspec>=0.12
Requires-Dist: platformdirs>=4.2
Requires-Dist: psutil>=5.9
Requires-Dist: pydantic>=2.7
Requires-Dist: rich>=13.7
Requires-Dist: structlog>=24.1
Requires-Dist: tomli>=2.0; python_version < '3.11'
Requires-Dist: typer[all]>=0.12
Requires-Dist: xxhash>=3.4
